wsimod/__init__.py
wsimod/__main__.py
wsimod/extensions.py
wsimod/validation.py
wsimod/arcs/__init__.py
wsimod/arcs/arcs.py
wsimod/core/__init__.py
wsimod/core/constants.py
wsimod/core/core.py
wsimod/demo/__init__.py
wsimod/demo/create_oxford.py
wsimod/nodes/__init__.py
wsimod/nodes/catchment.py
wsimod/nodes/demand.py
wsimod/nodes/distribution.py
wsimod/nodes/land.py
wsimod/nodes/nodes.py
wsimod/nodes/nutrient_pool.py
wsimod/nodes/sewer.py
wsimod/nodes/storage.py
wsimod/nodes/tanks.py
wsimod/nodes/waste.py
wsimod/nodes/wtw.py
wsimod/orchestration/__init__.py
wsimod/orchestration/model.py
wsimod-0.8.1.dist-info/METADATA
wsimod-0.8.1.dist-info/WHEEL
wsimod-0.8.1.dist-info/entry_points.txt
wsimod-0.8.1.dist-info/licenses/LICENSE
wsimod-0.8.1.dist-info/RECORD
