Metadata-Version: 2.4
Name: wsimod
Version: 0.8.1
Summary: WSIMOD is for simulating water quality and quantity
Author-email: Barnaby Dobson <b.dobson@imperial.ac.uk>, Imperial College London RSE Team <ict-rse-team@imperial.ac.uk>
License: BSD 3-Clause License
License-File: LICENSE
Requires-Python: >=3.9
Requires-Dist: dill
Requires-Dist: pandas
Requires-Dist: pyarrow
Requires-Dist: pyyaml
Requires-Dist: tqdm
Provides-Extra: demos
Requires-Dist: geopandas; extra == 'demos'
Requires-Dist: matplotlib; extra == 'demos'
Requires-Dist: shapely; extra == 'demos'
Provides-Extra: dev
Requires-Dist: black; extra == 'dev'
Requires-Dist: geopandas; extra == 'dev'
Requires-Dist: matplotlib; extra == 'dev'
Requires-Dist: pip-tools; extra == 'dev'
Requires-Dist: pre-commit; extra == 'dev'
Requires-Dist: pytest; extra == 'dev'
Requires-Dist: pytest-cov; extra == 'dev'
Requires-Dist: ruff; extra == 'dev'
Requires-Dist: shapely; extra == 'dev'
Provides-Extra: doc
Requires-Dist: geopandas; extra == 'doc'
Requires-Dist: matplotlib; extra == 'doc'
Requires-Dist: mkdocs; extra == 'doc'
Requires-Dist: mkdocs-autorefs; extra == 'doc'
Requires-Dist: mkdocs-bibtex; extra == 'doc'
Requires-Dist: mkdocs-coverage; extra == 'doc'
Requires-Dist: mkdocs-gen-files; extra == 'doc'
Requires-Dist: mkdocs-jupyter; extra == 'doc'
Requires-Dist: mkdocs-material; extra == 'doc'
Requires-Dist: mkdocs-material-extensions; extra == 'doc'
Requires-Dist: mkdocstrings[python]; extra == 'doc'
Requires-Dist: pypandoc; extra == 'doc'
Requires-Dist: shapely; extra == 'doc'
Requires-Dist: tabulate; extra == 'doc'
